[
{
"id": 1,
"name": "Geezard",
"level": 1,
"type": "Monster",
"element": "none",
"stats": 
    {
     "top": 1,
    "left": 5,
    "bottom": 1,
    "right": 4
    }   
},
{
"id": 2,
"name": "Funguar",
"level": 1,
"type": "Monster",
"element": "none",
"stats": 
    {
     "top": 5,
    "left": 3,
    "bottom": 1,
    "right": 1
    }
},
{
"id": 3,
"name": "Bite Bug",
"level": 1,
"type": "Monster",
"element": "none",
"stats": 
    { "top": 1,
    "left": 5,
    "bottom": 3,
    "right": 3
    }
},
{
"id": 4,
"name": "Red Bat",
"level": 1,
"type": "Monster",
"element": "none",
"stats": 
    { "top": 6,
    "left": 2,
    "bottom": 1,
    "right": 1
    }
},
{
"id": 5,
"name": "Blobra",
"level": 1,
"type": "Monster",
"element": "none",
"stats": 
    { "top": 2,
    "left": 5,
    "bottom": 1,
    "right": 3
    }
},
{
"id": 6,
"name": "Gayla",
"level": 1,
"type": "Monster",
"element": "Thunder",
"stats": 
    { "top": 2,
    "left": 4,
    "bottom": 4,
    "right": 1
    }
},
{
"id": 7,
"name": "Gesper",
"level": 1,
"type": "Monster",
"element": "none",
"stats": 
    { "top": 1,
    "left": 1,
    "bottom": 4,
    "right": 5
    }
},
{
"id": 8,
"name": "Fastitocalon-F",
"level": 1,
"type": "Monster",
"element": "Earth",
"stats": 
    { "top": 3,
    "left": 1,
    "bottom": 2,
    "right": 5
    }
},
{
"id": 9,
"name": "Blood Soul",
"level": 1,
"type": "Monster",
"element": "none",
"stats": 
    { "top": 2,
    "left": 1,
    "bottom": 6,
    "right": 1
    }
},
{
"id": 10,
"name": "Caterchipillar",
"level": 1,
"type": "Monster",
"element": "none",
"stats": 
    { "top": 4,
    "left": 3,
    "bottom": 4,
    "right": 2
    }
},
{
"id": 11,
"name": "Cockatrice",
"level": 1,
"type": "Monster",
"element": "Thunder",
"stats": 
    { "top": 2,
    "left": 6,
    "bottom": 2,
    "right": 1
    }
},
{
"id": 12,
"name": "Grat",
"level": 2,
"type": "Monster",
"element": "none",
"stats": 
    { "top": 7,
    "left": 1,
    "bottom": 3,
    "right": 1
    }
},
{
"id": 13,
"name": "Buel",
"level": 2,
"type": "Monster",
"element": "none",
"stats": 
    { "top": 6,
    "left": 3,
    "bottom": 2,
    "right": 2
    }
},
{
"id": 14,
"name": "Mesmerize",
"level": 2,
"type": "Monster",
"element": "none",
"stats": 
    { "top": 5,
    "left": 4,
    "bottom": 3,
    "right": 3
    }
},
{
"id": 15,
"name": "Glacial Eye",
"level": 2,
"type": "Monster",
"element": "Ice",
"stats": 
    { "top": 6,
    "left": 3,
    "bottom": 4,
    "right": 1
    }
},
{
"id": 16,
"name": "Belhelmel",
"level": 2,
"type": "Monster",
"element": "none",
"stats": 
    { "top": 3,
    "left": 3,
    "bottom": 5,
    "right": 4
    }
},
{
"id": 17,
"name": "Thrustaevis",
"level": 2,
"type": "Monster",
"element": "Wind",
"stats": 
    { "top": 5,
    "left": 5,
    "bottom": 2,
    "right": 3
    }
},
{
"id": 18,
"name": "Anacondaur",
"level": 2,
"type": "Monster",
"element": "Poison",
"stats": 
    { "top": 5,
    "left": 5,
    "bottom": 3,
    "right": 1
    }
},
{
"id": 19,
"name": "Creeps",
"level": 2,
"type": "Monster",
"element": "Thunder",
"stats": 
    { "top": 5,
    "left": 2,
    "bottom": 5,
    "right": 2
    }
},
{
"id": 20,
"name": "Grendel",
"level": 2,
"type": "Monster",
"element": "Thunder",
"stats": 
    { "top": 4,
    "left": 2,
    "bottom": 5,
    "right": 4
    }
},
{
"id": 21,
"name": "Jelleye",
"level": 2,
"type": "Monster",
"element": "none",
"stats": 
    { "top": 3,
    "left": 7,
    "bottom": 1,
    "right": 2
    }
},
{
"id": 22,
"name": "Grand Mantis",
"level": 2,
"type": "Monster",
"element": "none",
"stats":    
    { "top": 5,
    "left": 3,
    "bottom": 5,
    "right": 2
    }
},
{
"id": 23,
"name": "Forbidden",
"level": 3,
"type": "Monster",
"element": "none",
"stats": 
    { "top": 6,
    "left": 2,
    "bottom": 3,
    "right": 6
    }
},
{
"id": 24,
"name": "Armadodo",
"level": 3,
"type": "Monster",
"element": "Earth",
"stats": 
    { "top": 6,
    "left": 6,
    "bottom": 1,
    "right": 3
    }
},
{
"id": 25,
"name": "Tri-Face",
"level": 3,
"type": "Monster",
"element": "Poison",
"stats": 
    { "top": 3,
    "left": 5,
    "bottom": 5,
    "right": 5
    }
},
{
"id": 26,
"name": "Fastitocalon",
"level": 3,
"type": "Monster",
"element": "Earth",
"stats": 
    { "top": 7,
    "left": 3,
    "bottom": 1,
    "right": 5
    }
},
{
"id": 27,
"name": "Snow Lion",
"level": 3,
"type": "Monster",
"element": "Ice",
"stats": 
    { "top": 7,
    "left": 3,
    "bottom": 5,
    "right": 1
    }
},
{
"id": 28,
"name": "Ochu",
"level": 3,
"type": "Monster",
"element": "none",
"stats": 
    { "top": 5,
    "left": 3,
    "bottom": 3,
    "right": 6
    }
},
{
"id": 29,
"name": "SAM08G",
"level": 3,
"type": "Monster",
"element": "Fire",
"stats": 
    { "top": 5,
    "left": 4,
    "bottom": 2,
    "right": 6
    }
},
{
"id": 30,
"name": "Death Claw",
"level": 3,
"type": "Monster",
"element": "Fire",
"stats": 
    { "top": 4,
    "left": 2,
    "bottom": 7,
    "right": 4
    }
},
{
"id": 31,
"name": "Cactuar",
"level": 3,
"type": "Monster",
"element": "none",
"stats": 
    { "top": 6,
    "left": 3,
    "bottom": 6,
    "right": 2
    }
},
{
"id": 32,
"name": "Tonberry",
"level": 3,
"type": "Monster",
"element": "none",
"stats": 
    { "top": 3,
    "left": 4,
    "bottom": 4,
    "right": 6
    }
},
{
"id": 33,
"name": "Abyss Worm",
"level": 3,
"type": "Monster",
"element": "Earth",
"stats": 
    { "top": 7,
    "left": 5,
    "bottom": 3,
    "right": 2
    }
},
{
"id": 34,
"name": "Turtapod",
"level": 4,
"type": "Monster",
"element": "none",
"stats": 
    { "top": 2,
    "left": 7,
    "bottom": 6,
    "right": 3
    }
},
{
"id": 35,
"name": "Vysage",
"level": 4,
"type": "Monster",
"element": "none",
"stats": 
    { "top": 6,
    "left": 5,
    "bottom": 4,
    "right": 5
    }
},
{
"id": 36,
"name": "T-Rexaur",
"level": 4,
"type": "Monster",
"element": "none",
"stats": 
    { "top": 4,
    "left": 7,
    "bottom": 2,
    "right": 6
    }
},
{
"id": 37,
"name": "Bomb",
"level": 4,
"type": "Monster",
"element": "Fire",
"stats": 
    { "top": 2,
    "left": 3,
    "bottom": 6,
    "right": 7
    }
},
{
"id": 38,
"name": "Blitz",
"level": 4,
"type": "Monster",
"element": "Thunder",
"stats": 
    { "top": 1,
    "left": 7,
    "bottom": 4,
    "right": 6
    }
},
{
"id": 39,
"name": "Wendigo",
"level": 4,
"type": "Monster",
"element": "none",
"stats": 
    { "top": 7,
    "left": 6,
    "bottom": 1,
    "right": 3
    }
},
{
"id": 40,
"name": "Torama",
"level": 4,
"type": "Monster",
"element": "none",
"stats": 
    { "top": 7,
    "left": 4,
    "bottom": 4,
    "right": 4
    }
},
{
"id": 41,
"name": "Imp",
"level": 4,
"type": "Monster",
"element": "none",
"stats": 
    { "top": 3,
    "left": 6,
    "bottom": 3,
    "right": 7
    }
},
{
"id": 42,
"name": "Blue Dragon",
"level": 4,
"type": "Monster",
"element": "Poison",
"stats": 
    { "top": 6,
    "left": 3,
    "bottom": 7,
    "right": 2
    }
},
{
"id": 43,
"name": "Adamantoise",
"level": 4,
"type": "Monster",
"element": "Earth",
"stats": 
    { "top": 4,
    "left": 6,
    "bottom": 5,
    "right": 5
    }
},
{
"id": 44,
"name": "Hexadragon",
"level": 4,
"type": "Monster",
"element": "Fire",
"stats": 
    { "top": 7,
    "left": 3,
    "bottom": 4,
    "right": 5
    }
},
{
"id": 45,
"name": "Iron Giant",
"level": 5,
"type": "Monster",
"element": "none",
"stats": 
    { "top": 6,
    "left": 5,
    "bottom": 6,
    "right": 5
    }
},
{
"id": 46,
"name": "Behemoth",
"level": 5,
"type": "Monster",
"element": "none",
"stats": 
    { "top": 3,
    "left": 7,
    "bottom": 5,
    "right": 6
    }
},
{
"id": 47,
"name": "Chimera",
"level": 5,
"type": "Monster",
"element": "Water",
"stats": 
    { "top": 7,
    "left": 3,
    "bottom": 5,
    "right": 6
    }
},
{
"id": 48,
"name": "PuPu",
"level": 5,
"type": "Monster",
"element": "none",
"stats": 
    { "top": 3,
    "left": 1,
    "bottom": 2,
    "right": 10
    }
},
{
"id": 49,
"name": "Elastoid",
"level": 5,
"type": "Monster",
"element": "none",
"stats": 
    { "top": 6,
    "left": 7,
    "bottom": 6,
    "right": 2
    }
},
{
"id": 50,
"name": "GIM47N",
"level": 5,
"type": "Monster",
"element": "none",
"stats": 
    { "top": 5,
    "left": 4,
    "bottom": 7,
    "right": 5
    }
},
{
"id": 51,
"name": "Malboro",
"level": 5,
"type": "Monster",
"element": "Poison",
"stats": 
    { "top": 7,
    "left": 2,
    "bottom": 4,
    "right": 7
    }
},
{
"id": 52,
"name": "Ruby Dragon",
"level": 5,
"type": "Monster",
"element": "Fire",
"stats": 
    { "top": 7,
    "left": 4,
    "bottom": 7,
    "right": 2
    }
},
{
"id": 53,
"name": "Elnoyle",
"level": 5,
"type": "Monster",
"element": "none",
"stats": 
    { "top": 5,
    "left": 6,
    "bottom": 7,
    "right": 3
    }
},
{
"id": 54,
"name": "Tonberry King",
"level": 5,
"type": "Monster",
"element": "none",
"stats": 
    { "top": 7,
    "left": 4,
    "bottom": 7,
    "right": 6
    }
},
{
"id": 55,
"name": "Wedge/Biggs",
"level": 5,
"type": "Monster",
"element": "none",
"stats": 
    { "top": 6,
    "left": 7,
    "bottom": 2,
    "right": 6
    }
},
{
"id": 56,
"name": "Fujin/Raijin",
"level": 6,
"type": "Boss",
"element": "none",
"stats": 
    { "top": 2,
    "left": 4,
    "bottom": 8,
    "right": 8
    }
},
{
"id": 57,
"name": "Elvoret",
"level": 6,
"type": "Boss",
"element": "Wind",
"stats": 
    { "top": 7,
    "left": 4,
    "bottom": 3,
    "right": 8
    }
},
{
"id": 58,
"name": "X-ATM092",
"level": 6,
"type": "Boss",
"element": "none",
"stats": 
    { "top": 4,
    "left": 3,
    "bottom": 7,
    "right": 8
    }
},
{
"id": 59,
"name": "Granaldo",
"level": 6,
"type": "Boss",
"element": "none",
"stats": 
    { "top": 7,
    "left": 5,
    "bottom": 8,
    "right": 2
    }
},
{
"id": 60,
"name": "Gerogero",
"level": 6,
"type": "Boss",
"element": "Poison",
"stats": 
    { "top": 1,
    "left": 3,
    "bottom": 8,
    "right": 8
    }
},
{
"id": 61,
"name": "Iguion",
"level": 6,
"type": "Boss",
"element": "none",
"stats": 
    { "top": 8,
    "left": 2,
    "bottom": 8,
    "right": 2
    }
},
{
"id": 62,
"name": "Abadon",
"level": 6,
"type": "Boss",
"element": "none",
"stats": 
    { "top": 6,
    "left": 5,
    "bottom": 4,
    "right": 8
    }
},
{
"id": 63,
"name": "Trauma",
"level": 6,
"type": "Boss",
"element": "none",
"stats": 
    { "top": 4,
    "left": 6,
    "bottom": 5,
    "right": 8
    }
},
{
"id": 64,
"name": "OilBoyle",
"level": 6,
"type": "Boss",
"element": "none",
"stats": 
    { "top": 1,
    "left": 8,
    "bottom": 4,
    "right": 8
    }
},
{
"id": 65,
"name": "Shumi Village",
"level": 6,
"type": "Boss",
"element": "none",
"stats": 
    { "top": 6,
    "left": 4,
    "bottom": 8,
    "right": 5
    }
},
{
"id": 66,
"name": "Krysta",
"level": 6,
"type": "Boss",
"element": "none",
"stats": 
    { "top": 7,
    "left": 1,
    "bottom": 8,
    "right": 5
    }
},
{
"id": 67,
"name": "Propagator",
"level": 7,
"type": "Boss",
"element": "none",
"stats": 
    { "top": 8,
    "left": 8,
    "bottom": 4,
    "right": 4
    }
},
{
"id": 68,
"name": "Jumbo Cactuar",
"level": 7,
"type": "Boss",
"element": "none",
"stats": 
    { "top": 8,
    "left": 4,
    "bottom": 4,
    "right": 8
    }
},
{
"id": 69,
"name": "Tri-Point",
"level": 7,
"type": "Boss",
"element": "Thunder",
"stats": 
    { "top": 8,
    "left": 8,
    "bottom": 2,
    "right": 5
    }
},
{
"id": 70,
"name": "Gargantua",
"level": 7,
"type": "Boss",
"element": "none",
"stats": 
    { "top": 5,
    "left": 8,
    "bottom": 6,
    "right": 6
    }
},
{
"id": 71,
"name": "Mobile Type 8",
"level": 7,
"type": "Boss",
"element": "none",
"stats": 
    { "top": 8,
    "left": 3,
    "bottom": 7,
    "right": 6
    }
},
{
"id": 72,
"name": "Sphinxara",
"level": 7,
"type": "Boss",
"element": "none",
"stats": 
    { "top": 8,
    "left": 8,
    "bottom": 5,
    "right": 3
    }
},
{
"id": 73,
"name": "Tiamat",
"level": 7,
"type": "Boss",
"element": "none",
"stats": 
    { "top": 8,
    "left": 4,
    "bottom": 5,
    "right": 8
    }
},
{
"id": 74,
"name": "BGH251F2",
"level": 7,
"type": "Boss",
"element": "none",
"stats": 
    { "top": 5,
    "left": 5,
    "bottom": 8,
    "right": 7
    }
},
{
"id": 75,
"name": "Red Giant",
"level": 7,
"type": "Boss",
"element": "none",
"stats": 
    { "top": 6,
    "left": 7,
    "bottom": 4,
    "right": 8
    }
},
{
"id": 76,
"name": "Catoblepas",
"level": 7,
"type": "Boss",
"element": "none",
"stats": 
    { "top": 1,
    "left": 7,
    "bottom": 7,
    "right": 8
    }
},
{
"id": 77,
"name": "Ultima Weapon",
"level": 7,
"type": "Boss",
"element": "none",
"stats": 
    { "top": 7,
    "left": 8,
    "bottom": 2,
    "right": 7
    }
},
{
"id": 78,
"name": "Chubby Chocobo",
"level": 8,
"type": "G.F.",
"element": "none",
"stats": 
    { "top": 4,
    "left": 9,
    "bottom": 8,
    "right": 4
    }
},
{
"id": 79,
"name": "Angelo",
"level": 8,
"type": "G.F.",
"element": "none",
"stats": 
    { "top": 9,
    "left": 3,
    "bottom": 7,
    "right": 6
    }
},
{
"id": 80,
"name": "Gilgamesh",
"level": 8,
"type": "G.F.",
"element": "none",
"stats": 
    { "top": 3,
    "left": 6,
    "bottom": 9,
    "right": 7
    }
},
{
"id": 81,
"name": "Mini Mog",
"level": 8,
"type": "G.F.",
"element": "none",
"stats": 
    { "top": 9,
    "left": 2,
    "bottom": 9,
    "right": 3
    }
},
{
"id": 82,
"name": "Chicobo",
"level": 8,
"type": "G.F.",
"element": "none",
"stats": 
    { "top": 9,
    "left": 4,
    "bottom": 8,
    "right": 4
    }
},
{
"id": 83,
"name": "Quezacotl",
"level": 8,
"type": "G.F.",
"element": "Thunder",
"stats": 
    { "top": 2,
    "left": 4,
    "bottom": 9,
    "right": 9
    }
},
{
"id": 84,
"name": "Shiva",
"level": 8,
"type": "G.F.",
"element": "Ice",
"stats": 
    { "top": 6,
    "left": 9,
    "bottom": 4,
    "right": 7
    }
},
{
"id": 85,
"name": "Ifrit",
"level": 8,
"type": "G.F.",
"element": "Fire",
"stats": 
    { "top": 9,
    "left": 8,
    "bottom": 2,
    "right": 6
    }
},
{
"id": 86,
"name": "Siren",
"level": 8,
"type": "G.F.",
"element": "none",
"stats": 
    { "top": 8,
    "left": 2,
    "bottom": 6,
    "right": 9
    }
},
{
"id": 87,
"name": "Sacred",
"level": 8,
"type": "G.F.",
"element": "Earth",
"stats": 
    { "top": 5,
    "left": 9,
    "bottom": 9,
    "right": 1
    }
},
{
"id": 88,
"name": "Minotaur",
"level": 8,
"type": "G.F.",
"element": "Earth",
"stats": 
    { "top": 9,
    "left": 9,
    "bottom": 2,
    "right": 5
    }
},
{
"id": 89,
"name": "Carbuncle",
"level": 9,
"type": "G.F.",
"element": "none",
"stats": 
    { "top": 8,
    "left": 4,
    "bottom": 10,
    "right": 4
    }
},
{
"id": 90,
"name": "Diablos",
"level": 9,
"type": "G.F.",
"element": "none",
"stats": 
    { "top": 5,
    "left": 3,
    "bottom": 8,
    "right": 10
    }
},
{
"id": 91,
"name": "Leviathan",
"level": 9,
"type": "G.F.",
"element": "Water",
"stats": 
    { "top": 7,
    "left": 7,
    "bottom": 1,
    "right": 10
    }
},
{
"id": 92,
"name": "Odin",
"level": 9,
"type": "G.F.",
"element": "none",
"stats": 
    { "top": 8,
    "left": 5,
    "bottom": 3,
    "right": 10
    }
},
{
"id": 93,
"name": "Pandemona",
"level": 9,
"type": "G.F.",
"element": "Wind",
"stats": 
    { "top": 10,
    "left": 7,
    "bottom": 7,
    "right": 1
    }
},
{
"id": 94,
"name": "Cerberus",
"level": 9,
"type": "G.F.",
"element": "none",
"stats": 
    { "top": 7,
    "left": 10,
    "bottom": 6,
    "right": 4
    }
},
{
"id": 95,
"name": "Alexander",
"level": 9,
"type": "G.F.",
"element": "Holy",
"stats": 
    { "top": 9,
    "left": 2,
    "bottom": 4,
    "right": 10
    }
},
{
"id": 96,
"name": "Phoenix",
"level": 9,
"type": "G.F.",
"element": "Fire",
"stats": 
    { "top": 7,
    "left": 10,
    "bottom": 7,
    "right": 2
    }
},
{
"id": 97,
"name": "Bahamut",
"level": 9,
"type": "G.F.",
"element": "none",
"stats": 
    { "top": 10,
    "left": 6,
    "bottom": 2,
    "right": 8
    }
},
{
"id": 98,
"name": "Doomtrain",
"level": 9,
"type": "G.F.",
"element": "Poison",
"stats": 
    { "top": 3,
    "left": 10,
    "bottom": 10,
    "right": 1
    }
},
{
"id": 99,
"name": "Eden",
"level": 9,
"type": "G.F.",
"element": "none",
"stats": 
    { "top": 4,
    "left": 10,
    "bottom": 9,
    "right": 4
    }
},
{
"id": 100,
"name": "Ward Zabac",
"level": 10,
"type": "Character",
"element": "none",
"stats": 
    { "top": 10,
    "left": 8,
    "bottom": 2,
    "right": 7
    }
},
{
"id": 101,
"name": "Kiros Seagill",
"level": 10,
"type": "Character",
"element": "none",
"stats": 
    { "top": 6,
    "left": 10,
    "bottom": 6,
    "right": 7
    }
},
{
"id": 102,
"name": "Laguna Loire",
"level": 10,
"type": "Character",
"element": "none",
"stats": 
    { "top": 5,
    "left": 9,
    "bottom": 3,
    "right": 10
    }
},
{
"id": 103,
"name": "Selphie Tilmitt",
"level": 10,
"type": "Character",
"element": "none",
"stats": 
    { "top": 10,
    "left": 4,
    "bottom": 6,
    "right": 8
    }
},
{
"id": 104,
"name": "Quistis Trepe",
"level": 10,
"type": "Character",
"element": "none",
"stats": 
    { "top": 9,
    "left": 2,
    "bottom": 10,
    "right": 6
    }
},
{
"id": 105,
"name": "Irvine Kinneas",
"level": 10,
"type": "Character",
"element": "none",
"stats": 
    { "top": 2,
    "left": 10,
    "bottom": 9,
    "right": 6
    }
},
{
"id": 106,
"name": "Zell Dincht",
"level": 10,
"type": "Character",
"element": "none",
"stats": 
    { "top": 8,
    "left": 6,
    "bottom": 10,
    "right": 5
    }
},
{
"id": 107,
"name": "Rinoa Heartilly",
"level": 10,
"type": "Character",
"element": "none",
"stats": 
    { "top": 4,
    "left": 10,
    "bottom": 2,
    "right": 10
    }
},
{
"id": 108,
"name": "Edea",
"level": 10,
"type": "Character",
"element": "none",
"stats": 
    { "top": 10,
    "left": 3,
    "bottom": 3,
    "right": 10
    }
},
{
"id": 109,
"name": "Seifer Almasy",
"level": 10,
"type": "Character",
"element": "none",
"stats": 
    { "top": 6,
    "left": 4,
    "bottom": 10,
    "right": 9
    }
},
{
"id": 110,
"name": "Squall Leonhart",
"level": 10,
"type": "Character",
"element": "none",
"stats": 
    { "top": 10,
    "left": 9,
    "bottom": 6,
    "right": 4
    }
},
{
"id": 111,
"name": "Pixelroy",
"level": 10,
"type": "Character",
"element": "none",
"stats": 
    { "top": 10,
    "left": 4,
    "bottom": 6,
    "right": 8
    }
}
]